sjtrade/__init__.py
sjtrade/data.py
sjtrade/position.py
sjtrade/simulation_shioaji.py
sjtrade/strategy.py
sjtrade/trader.py
sjtrade/utils.py
sjtrade/io/__init__.py
sjtrade/io/file.py
sjtrade-1.1.1.dist-info/WHEEL
sjtrade-1.1.1.dist-info/METADATA
sjtrade-1.1.1.dist-info/RECORD
