Metadata-Version: 2.1
Name: sjtrade
Version: 1.1.1
Summary: sjtrade
Author-email: yvictor <yvictor3141@gmail.com>
Requires-Python: >=3.6
Classifier: Development Status :: 5 - Production/Stable
Classifier: Intended Audience :: Developers
Classifier: Intended Audience :: Financial and Insurance Industry
Classifier: Programming Language :: Python :: 3
Classifier: Programming Language :: Python :: 3.6
Classifier: Programming Language :: Python :: 3.7
Classifier: Programming Language :: Python :: 3.8
Classifier: Programming Language :: Python :: 3.9
Classifier: Programming Language :: Python :: 3.10
Classifier: Programming Language :: Python :: 3.11
Classifier: Topic :: Software Development :: Libraries :: Python Modules
Classifier: Topic :: Office/Business :: Financial
Classifier: Topic :: Office/Business :: Financial :: Investment
Requires-Dist: shioaji>=1.0
Requires-Dist: loguru
Requires-Dist: rs2py
Requires-Dist: black ; extra == "test"
Requires-Dist: pytest>=7.1.2 ; extra == "test"
Requires-Dist: pytest-freezegun ; extra == "test"
Requires-Dist: pytest-mock ; extra == "test"
Requires-Dist: pytest-cov ; extra == "test"
Requires-Dist: codecov ; extra == "test"
Project-URL: Home, https://github.com/Yvictor/sjtrade
Provides-Extra: test
